pykeyboard/__init__.py
pykeyboard/builder.py
pykeyboard/errors.py
pykeyboard/hooks.py
pykeyboard/inline_keyboard.py
pykeyboard/keyboard_base.py
pykeyboard/performance.py
pykeyboard/reply_keyboard.py
pykeyboard/utils.py
pykeyboard/visualization.py
pykeyboard_kurigram-0.2.4.dist-info/LICENSE
pykeyboard_kurigram-0.2.4.dist-info/METADATA
pykeyboard_kurigram-0.2.4.dist-info/WHEEL
pykeyboard_kurigram-0.2.4.dist-info/RECORD
