Metadata-Version: 2.3
Name: pykeyboard-kurigram
Version: 0.2.4
Summary: Best Keyboard and Pagination for the Kurigram Library.
License: MIT
Author: Johnnie
Author-email: expose-bright-coat@duck.com
Requires-Python: >=3.9,<4.0
Classifier: License :: OSI Approved :: MIT License
Classifier: Programming Language :: Python :: 3
Classifier: Programming Language :: Python :: 3.9
Classifier: Programming Language :: Python :: 3.10
Classifier: Programming Language :: Python :: 3.11
Classifier: Programming Language :: Python :: 3.12
Classifier: Programming Language :: Python :: 3.13
Requires-Dist: kurigram (>=2.1.35,<3.0.0)
Requires-Dist: pydantic (>=2.11.7,<3.0.0)
Project-URL: documentation, https://johnnie-610.github.io/pykeyboard
Project-URL: repository, https://github.com/johnnie-610/pykeyboard
